README.rst
setup.py
tg_webhook/__init__.py
tg_webhook.egg-info/PKG-INFO
tg_webhook.egg-info/SOURCES.txt
tg_webhook.egg-info/dependency_links.txt
tg_webhook.egg-info/not-zip-safe
tg_webhook.egg-info/requires.txt
tg_webhook.egg-info/top_level.txt