Metadata-Version: 1.1
Name: tg-webhook
Version: 0.1.1
Summary: A TurboGears webhook plugin
Home-page: https://github.com/sthima/tg-webhook
Author: Sthima
Author-email: sthima@sthima.com.br
License: MIT
Keywords: turbogears plugin webhook api
Platform: UNKNOWN
Classifier: Development Status :: 3 - Alpha
Classifier: Intended Audience :: Developers
Classifier: Topic :: Software Development :: Libraries :: Python Modules
Classifier: License :: OSI Approved :: MIT License
Classifier: Programming Language :: Python :: 2
Classifier: Programming Language :: Python :: 2.7
